rikai/contrib/ros/__init__.py
rikai/contrib/ros/convert.py
rikai_ros-0.0.1.dist-info/METADATA
rikai_ros-0.0.1.dist-info/WHEEL
rikai_ros-0.0.1.dist-info/top_level.txt
rikai_ros-0.0.1.dist-info/RECORD
